codes/exam/problem_7/problem_7.v
module problem_7(a, b, c, F);
  input a;
  input b;
  input c;
  output reg F;

  always @ (a, b, c) begin
    F = ~ a * ~ b * c + a * b * ~ c + a * b * c;
  end
endmodule

codes/exam/problem_7/problem_7_tb.v
`timescale 1 ns / 100 ps
module problem_7_tb();
  reg a;
  reg b;
  reg c;
  wire F;
  integer ii;

  problem_7 UUT ( .a(a), .b(b), .c(c), .F(F));

  reg [20*8-1:0] str;

  initial begin

    for (ii=0; ii<8; ii=ii+1) begin
      {a, b, c} = ii; #10;
      $display("a=%b, b=%b, c=%b, F=%b\n", a, b, c, F);
    end

    $display("Test done.\n");
  end
endmodule

codes/exam/problem_7/problem_7.vcd
$date
	Wed Feb 13 14:22:21 2019
$end
$version
	Icarus Verilog
$end
$timescale
	100ps
$end
$scope module problem_7_tb $end
$scope module UUT $end
$var wire 1 ! a $end
$var wire 1 " b $end
$var wire 1 # c $end
$var reg 1 $ F $end
$upscope $end
$upscope $end
$enddefinitions $end
#0
$dumpvars
0$
0#
0"
0!
$end
#100
1$
1#
#200
0$
1"
0#
#300
1#
#400
1!
0"
0#
#500
1#
#600
1$
1"
0#
#700
1#
